bball_data/__init__.py
bball_data-0.1.2.dist-info/METADATA
bball_data-0.1.2.dist-info/WHEEL
bball_data-0.1.2.dist-info/RECORD
